class_settings/__init__.py
class_settings/env.py
class_settings/importers.py
class_settings/options.py
class_settings/parsers.py
class_settings/settings.py
class_settings/utils.py
django_class_settings-0.2.0.dist-info/LICENSE
django_class_settings-0.2.0.dist-info/WHEEL
django_class_settings-0.2.0.dist-info/METADATA
django_class_settings-0.2.0.dist-info/RECORD
