Metadata-Version: 2.1
Name: django-class-settings
Version: 0.2.0
Summary: Effortless class-based settings for Django.
Home-page: https://github.com/orlnub123/django-class-settings
License: MIT
Keywords: django,settings,configuration
Author: orlnub123
Author-email: orlnub123@gmail.com
Requires-Python: >=3.5,<4.0
Classifier: Development Status :: 3 - Alpha
Classifier: Environment :: Web Environment
Classifier: Framework :: Django
Classifier: Framework :: Django :: 1.11
Classifier: Framework :: Django :: 2.0
Classifier: Framework :: Django :: 2.1
Classifier: Framework :: Django :: 2.2
Classifier: Framework :: Django :: 3.0
Classifier: Intended Audience :: Developers
Classifier: License :: OSI Approved :: MIT License
Classifier: Operating System :: OS Independent
Classifier: Programming Language :: Python :: 3
Classifier: Programming Language :: Python :: 3.5
Classifier: Programming Language :: Python :: 3.6
Classifier: Programming Language :: Python :: 3.7
Classifier: Programming Language :: Python :: 3.8
Classifier: Topic :: Software Development :: Libraries :: Python Modules
Classifier: Topic :: Utilities
Requires-Dist: django
Requires-Dist: python-dotenv (>=0.7)
Project-URL: Documentation, https://django-class-settings.readthedocs.io/
Project-URL: Repository, https://github.com/orlnub123/django-class-settings
